servecmd/__init__.py
servecmd/__main__.py
servecmd/client.py
servecmd/cmd_manager.py
servecmd/cmd_session.py
servecmd/conf.py
servecmd/models.py
servecmd/server.py
servecmd/util.py
servecmd-0.0.17.dist-info/LICENSE
servecmd-0.0.17.dist-info/METADATA
servecmd-0.0.17.dist-info/WHEEL
servecmd-0.0.17.dist-info/entry_points.txt
servecmd-0.0.17.dist-info/RECORD
